MANIFEST.in
README.md
pyproject.toml
setup.cfg
setup.py
netbox_qr/__init__.py
netbox_qr/netbox_qr.py
netbox_qr/template_content.py
netbox_qr.egg-info/PKG-INFO
netbox_qr.egg-info/SOURCES.txt
netbox_qr.egg-info/dependency_links.txt
netbox_qr.egg-info/not-zip-safe
netbox_qr.egg-info/requires.txt
netbox_qr.egg-info/top_level.txt
netbox_qr/fonts/LICENSE.txt
netbox_qr/fonts/Roboto-Black.ttf
netbox_qr/fonts/Roboto-BlackItalic.ttf
netbox_qr/fonts/Roboto-Bold.ttf
netbox_qr/fonts/Roboto-BoldItalic.ttf
netbox_qr/fonts/Roboto-Italic.ttf
netbox_qr/fonts/Roboto-Light.ttf
netbox_qr/fonts/Roboto-LightItalic.ttf
netbox_qr/fonts/Roboto-Medium.ttf
netbox_qr/fonts/Roboto-MediumItalic.ttf
netbox_qr/fonts/Roboto-Regular.ttf
netbox_qr/fonts/Roboto-Thin.ttf
netbox_qr/fonts/Roboto-ThinItalic.ttf
netbox_qr/templates/netbox_qr/qr.html